oam/__init__.py
oam/preprocess/__init__.py
oam/score/__init__.py
oam/score/isolation_path.py
oam/search/__init__.py
oam/search/simple_combination.py
oam/visualization/__init__.py
python_oam-0.7.dist-info/LICENSE
python_oam-0.7.dist-info/METADATA
python_oam-0.7.dist-info/WHEEL
python_oam-0.7.dist-info/top_level.txt
python_oam-0.7.dist-info/RECORD
