Metadata-Version: 2.1
Name: python-oam
Version: 0.7
Summary: OAM toolbox made by the community to the community
Home-page: UNKNOWN
Author: ['Rodrigo Faria', 'Tiago Colli']
Author-email: rodrigo.f.ss@uol.com.br
License: MIT
Keywords: oam,outlier,aspect,mining,data,explicability,outlying
Platform: UNKNOWN
Requires-Dist: pandas (==1.3.2)
Requires-Dist: seaborn (==0.11.2)
Requires-Dist: tqdm (==4.62.0)
